mbfunc/__init__.py
mbfunc/dehalo/__init__.py
mbfunc/dehalo/dehalo.py
mbfunc/enhance/__init__.py
mbfunc/enhance/sharpen.py
mbfunc/havsfunc/__init__.py
mbfunc/havsfunc/havsfunc.py
mbfunc/mask/__init__.py
mbfunc/mask/mask.py
mbfunc/mvsfunc/__init__.py
mbfunc/mvsfunc/mvsfunc.py
mbfunc/nnedi3_resample/__init__.py
mbfunc/nnedi3_resample/nnedi3_resample.py
mbfunc/xvs/LICENSE
mbfunc/xvs/__init__.py
mbfunc/xvs/xvs.py
mbfunc/zvs/LICENSE
mbfunc/zvs/__init__.py
mbfunc/zvs/zvs.py
mbfunc-0.2.0.dist-info/LICENSE
mbfunc-0.2.0.dist-info/METADATA
mbfunc-0.2.0.dist-info/WHEEL
mbfunc-0.2.0.dist-info/RECORD
