Metadata-Version: 2.1
Name: mbfunc
Version: 0.2.0
Summary: mbf's VapourSynth functions
Home-page: https://github.com/EutropicAI/mbfunc
License: GPL-3.0-only
Author: EutropicAI
Requires-Python: >=3.9,<4.0
Classifier: License :: OSI Approved :: GNU General Public License v3 (GPLv3)
Classifier: Programming Language :: Python :: 3
Classifier: Programming Language :: Python :: 3.9
Classifier: Programming Language :: Python :: 3.10
Classifier: Programming Language :: Python :: 3.11
Classifier: Programming Language :: Python :: 3.12
Project-URL: Repository, https://github.com/EutropicAI/mbfunc
